sphinx_multiversion/__init__.py
sphinx_multiversion/__main__.py
sphinx_multiversion/git.py
sphinx_multiversion/main.py
sphinx_multiversion/sphinx.py
sphinx_multiversion-0.2.4.dist-info/LICENSE
sphinx_multiversion-0.2.4.dist-info/METADATA
sphinx_multiversion-0.2.4.dist-info/WHEEL
sphinx_multiversion-0.2.4.dist-info/entry_points.txt
sphinx_multiversion-0.2.4.dist-info/top_level.txt
sphinx_multiversion-0.2.4.dist-info/RECORD
